rx_carousel/carousel.py
reflex_carousel-0.0.1.dist-info/METADATA
reflex_carousel-0.0.1.dist-info/WHEEL
reflex_carousel-0.0.1.dist-info/top_level.txt
reflex_carousel-0.0.1.dist-info/RECORD
